[
  {
    "formattedName": "Linda Gunshefski",
    "pdcId": "GUNSL--992",
    "altNames": [
      "Linda Gunshefski"
    ]
  },
  {
    "formattedName": "Craig Woodard",
    "pdcId": "WOODC--902",
    "altNames": [
      "Craig R Woodard"
    ]
  },
  {
    "formattedName": "Stephanie Barnard",
    "pdcId": "BARNS--909",
    "altNames": [
      "Stephanie Barnard"
    ]
  },
  {
    "formattedName": "Joe Schmick",
    "pdcId": "SCHMJ  111",
    "altNames": [
      "Joe Schmick"
    ]
  },
  {
    "formattedName": "Blanche Barajas",
    "pdcId": "BARAB  301",
    "altNames": [
      "Blanche Barajas"
    ]
  },
  {
    "formattedName": "Rocky Mullen",
    "pdcId": "MULLR  301",
    "altNames": [
      "RODNEY J MULLEN  (Rocky Mullen)"
    ]
  },
  {
    "formattedName": "Bronson Brown",
    "pdcId": "BROWB--336",
    "altNames": [
      "Bronson Joe Brown (Bronson J. Brown)"
    ]
  },
  {
    "formattedName": "Jeff Smart",
    "pdcId": "SMARJ--352",
    "altNames": [
      "Jeffrey J Smart (Jeff J Smart)"
    ]
  },
  {
    "formattedName": "Perry Dozier",
    "pdcId": "DOZIP  361",
    "altNames": [
      "DOZIER PERRY L (Perry Dozier)"
    ]
  },
  {
    "formattedName": "Skyler Rude",
    "pdcId": "RUDES  504",
    "altNames": [
      "SKYLER D. RUDE (Skyler Rude)"
    ]
  },
  {
    "formattedName": "Jerome Delvin",
    "pdcId": "DELVJ  352",
    "altNames": [
      "DELVIN JEROME L II (Jerome Delvin)"
    ]
  },
  {
    "formattedName": "Mark Schoesler",
    "pdcId": "SCHOM  169",
    "altNames": [
      "Mark Schoesler (Mark G. Schoesler)"
    ]
  },
  {
    "formattedName": "Shawn Sant",
    "pdcId": "SANTS  301",
    "altNames": [
      "Shawn P Sant (Shawn P. Sant)"
    ]
  },
  {
    "formattedName": "Stephen Bauman",
    "pdcId": "BAUMS--301",
    "altNames": [
      "Stephen Bauman"
    ]
  },
  {
    "formattedName": "Mark Klicker",
    "pdcId": "KLICM--362",
    "altNames": [
      "Mark R Klicker (Mark Klicker)"
    ]
  },
  {
    "formattedName": "Pam Kohlmeier",
    "pdcId": "KOHLP--115",
    "altNames": [
      "Pamela Kohlmeier (Pam Kohlmeier)"
    ]
  },
  {
    "formattedName": "Patrick Miller",
    "pdcId": "MILLP--916",
    "altNames": [
      "Patrick Miller"
    ]
  },
  {
    "formattedName": "April Connors",
    "pdcId": "CONNA--861",
    "altNames": [
      "April R Connors (April Connors)"
    ]
  },
  {
    "formattedName": "Mary Dye",
    "pdcId": "DYE M  347",
    "altNames": [
      "Mary L Dye (Mary Dye)"
    ]
  },
  {
    "formattedName": "John Christenson",
    "pdcId": "CHRIJ--336",
    "altNames": [
      "John Eric Christenson (John Christenson)"
    ]
  },
  {
    "formattedName": "Ana Ruiz Kennedy",
    "pdcId": "KENNA--110",
    "altNames": [
      "Ana Ruiz Kennedy"
    ]
  },
  {
    "formattedName": "Kari Isaacson",
    "pdcId": "ISAAK--513",
    "altNames": [
      "Kari Isaacson"
    ]
  }
]