[
  {
    "id": "barns-909-funding",
    "candidate": "BARNS--909",
    "unique_donors": 230,
    "total_raised": 95309,
    "total_cash": null,
    "total_in_kind": null,
    "donors": [
      "barns-909-bouchey-joel",
      "barns-909-bouchey-kevin",
      "barns-909-bouchee-renee",
      "barns-909-davenport-thomas",
      "barns-909-henderson-destry",
      "barns-909-feil-alma",
      "barns-909-heath-rick",
      "barns-909-funk-sarah",
      "barns-909-ashby-steven",
      "barns-909-the-nichols-group-government-relations",
      "barns-909-hedengren-david",
      "barns-909-hedengren-marian",
      "barns-909-burton-len",
      "barns-909-associated-builders-and-contractors-inland-pacific-chapter-inc",
      "barns-909-agri-beef-management",
      "barns-909-miscellaneous-receipts",
      "barns-909-washington-hospitality-association-pac",
      "barns-909-puget-sound-energy",
      "barns-909-chevron-policy-govt-publ-affairs",
      "barns-909-washington-oil-marketers-assoc-pac",
      "barns-909-comcast-financial-agency-corporation",
      "barns-909-mc-bride-public-affairs-llc",
      "barns-909-northwest-natural-gas",
      "barns-909-arbaugh-associates-llc",
      "barns-909-walmart-inc",
      "barns-909-mullen-randy",
      "barns-909-roach-john",
      "barns-909-roach-nancy",
      "barns-909-washington-optometric-pac",
      "barns-909-small-contributions",
      "barns-909-hill-andrew",
      "barns-909-minuteman-press",
      "barns-909-washington-food-industry-association",
      "barns-909-kochpac-koch-industries-inc-pac",
      "barns-909-washington-state-auto-dealers-pac",
      "barns-909-iupat-political-action-together-legislative-education-committee",
      "barns-909-ray-e-l",
      "barns-909-neibaur-vicki",
      "barns-909-arneson-jim",
      "barns-909-short-ken",
      "barns-909-delvin-jerome",
      "barns-909-shimek-jaime",
      "barns-909-mick-westin",
      "barns-909-renz-liz",
      "barns-909-nelson-katie",
      "barns-909-umc-inc",
      "barns-909-garcia-raul",
      "barns-909-peurrung-anthony",
      "barns-909-novakovich-shannon",
      "barns-909-novakovich-michael",
      "barns-909-blasdel-melissa",
      "barns-909-morris-jeff",
      "barns-909-washington-technology-industry-association-wtia",
      "barns-909-cypress-creek-renewables-development-llc",
      "barns-909-law-office-of-patrick-d-mc-burney",
      "barns-909-lampson-william",
      "barns-909-lampson-kate",
      "barns-909-smitt-gary",
      "barns-909-smitt-donna",
      "barns-909-grabner-reagan",
      "barns-909-grabner-lindsey",
      "barns-909-ace-brian",
      "barns-909-henry-staci",
      "barns-909-raymond-james",
      "barns-909-barber-shannon",
      "barns-909-huber-monty",
      "barns-909-fielding-cody",
      "barns-909-fielding-candace",
      "barns-909-hollingsworth-chris",
      "barns-909-carlen-diana",
      "barns-909-hale-kari",
      "barns-909-ruiz-javier",
      "barns-909-hatch-la-wanda",
      "barns-909-moody-dean",
      "barns-909-spanner-bruce",
      "barns-909-spanner-mary",
      "barns-909-brunson-kim",
      "barns-909-sparkling-sensation-inc",
      "barns-909-christensen",
      "barns-909-parr-robert",
      "barns-909-reeploeg-david",
      "barns-909-heaston-suzanne",
      "barns-909-heaston-dale",
      "barns-909-haller-david",
      "barns-909-haller-robin",
      "barns-909-sandlin-bryan",
      "barns-909-sandlin-deborah",
      "barns-909-reyes-charles",
      "barns-909-massey-consulting-llc",
      "barns-909-simmons-steven",
      "barns-909-simmons-shirley",
      "barns-909-reeploeg-gretchen",
      "barns-909-clarke-bill",
      "barns-909-house-republican-organizational-committee",
      "barns-909-delta-dental",
      "barns-909-reynolds-american-inc-rai-services-company",
      "barns-909-bilskis-richard",
      "barns-909-west-staci",
      "barns-909-richey-jodi",
      "barns-909-richey-bob",
      "barns-909-wilson-claudia",
      "barns-909-ownbey-nikki",
      "barns-909-jacobs-ryan",
      "barns-909-jacobs-morgen",
      "barns-909-casey-paul",
      "barns-909-hastings-colin",
      "barns-909-howard-diahann",
      "barns-909-bassett-melanie",
      "barns-909-morris-john",
      "barns-909-tri-city-eyes",
      "barns-909-t-mobile-usa-inc",
      "barns-909-mattson-lori",
      "barns-909-gerber-michele",
      "barns-909-gerber-eric",
      "barns-909-francik-rebecca",
      "barns-909-francik-joseph",
      "barns-909-dietrich-darrick",
      "barns-909-salon-remedi",
      "barns-909-brewer-glenda",
      "barns-909-mc-curley-dealerships",
      "barns-909-arbaugh-david",
      "barns-909-washington-forest-protection-association",
      "barns-909-sabey-corporation",
      "barns-909-at-t-services-inc",
      "barns-909-wa-state-tree-fruit-association-pac",
      "barns-909-potato-pac",
      "barns-909-cattle-pac",
      "barns-909-amazon-com-services-llc",
      "barns-909-altria-client-services-llc",
      "barns-909-packaging-corporation-of-america",
      "barns-909-associated-builders-and-contractors-of-wester-washington-pac",
      "barns-909-amr-holdco-inc",
      "barns-909-davita",
      "barns-909-puget-sound-chapter-neca-pac",
      "barns-909-lumen-technologies-service-group",
      "barns-909-stubbs-ashley",
      "barns-909-davenport-jennifer",
      "barns-909-b-4-development-and-consulting-llc",
      "barns-909-thompson-trent",
      "barns-909-thompson-elizabeth",
      "barns-909-helms-karen",
      "barns-909-helms-jason",
      "barns-909-davidson-duane",
      "barns-909-center-vision-contact-lens-clinic",
      "barns-909-washington-affordable-housing-council",
      "barns-909-washington-society-of-cpas-pac",
      "barns-909-macpac",
      "barns-909-washington-electric-cooperative-pac",
      "barns-909-eschenberg-john",
      "barns-909-osborne-andrew",
      "barns-909-puget-sound-pilots-pac",
      "barns-909-build-east-pac",
      "barns-909-door-dash-inc",
      "barns-909-washington-aggregates-concrete-association",
      "barns-909-cullen-greg",
      "barns-909-elenbaas-dan",
      "barns-909-buena-vista-property-management",
      "barns-909-cal-portland-company",
      "barns-909-washington-wheat-pac",
      "barns-909-avista-corp",
      "barns-909-the-boeing-company-pac",
      "barns-909-iron-workers-district-council-of-the-pacific-northwest-pac",
      "barns-909-muckleshoot-indian-tribe",
      "barns-909-spokane-teachers-credit-union",
      "barns-909-washington-beverage-association-pac",
      "barns-909-washington-state-assoc-of-fire-chiefs-pac",
      "barns-909-bybee-brett",
      "barns-909-credit-union-legislative-action-fund",
      "barns-909-pemco-mutual-insurance-company",
      "barns-909-moveit-inc",
      "barns-909-cascade-natural-gas-corporation",
      "barns-909-life-science-washington-pac",
      "barns-909-fisher-darrel",
      "barns-909-fisher-a-jeanne",
      "barns-909-broadband-communications-association-of-washington-pac",
      "barns-909-american-chemistry-council",
      "barns-909-northwest-grocery-association-wa-pac"
    ],
    "donations": [
      "barns-909-bouchey-joel-2024-0",
      "barns-909-bouchey-kevin-2024-1",
      "barns-909-bouchee-renee-2024-2",
      "barns-909-davenport-thomas-2024-3",
      "barns-909-henderson-destry-2024-4",
      "barns-909-feil-alma-2024-5",
      "barns-909-heath-rick-2024-6",
      "barns-909-funk-sarah-2024-7",
      "barns-909-ashby-steven-2024-8",
      "barns-909-the-nichols-group-government-relations-2024-9",
      "barns-909-hedengren-david-2024-10",
      "barns-909-hedengren-marian-2024-11",
      "barns-909-burton-len-2024-12",
      "barns-909-associated-builders-and-contractors-inland-pacific-chapter-inc-2024-13",
      "barns-909-agri-beef-management-2024-14",
      "barns-909-miscellaneous-receipts-2024-15",
      "barns-909-washington-hospitality-association-pac-2024-16",
      "barns-909-puget-sound-energy-2024-17",
      "barns-909-puget-sound-energy-2024-18",
      "barns-909-chevron-policy-govt-publ-affairs-2024-19",
      "barns-909-washington-oil-marketers-assoc-pac-2024-20",
      "barns-909-comcast-financial-agency-corporation-2024-21",
      "barns-909-mc-bride-public-affairs-llc-2024-22",
      "barns-909-northwest-natural-gas-2024-23",
      "barns-909-arbaugh-associates-llc-2024-24",
      "barns-909-walmart-inc-2024-25",
      "barns-909-mullen-randy-2024-26",
      "barns-909-roach-john-2024-27",
      "barns-909-roach-nancy-2024-28",
      "barns-909-washington-optometric-pac-2024-29",
      "barns-909-small-contributions-2024-30",
      "barns-909-small-contributions-2024-31",
      "barns-909-hill-andrew-2024-32",
      "barns-909-minuteman-press-2024-33",
      "barns-909-washington-food-industry-association-2024-34",
      "barns-909-kochpac-koch-industries-inc-pac-2024-35",
      "barns-909-washington-hospitality-association-pac-2024-36",
      "barns-909-washington-hospitality-association-pac-2024-37",
      "barns-909-washington-state-auto-dealers-pac-2024-38",
      "barns-909-washington-optometric-pac-2024-39",
      "barns-909-washington-optometric-pac-2024-40",
      "barns-909-iupat-political-action-together-legislative-education-committee-2024-41",
      "barns-909-ray-e-l-2024-42",
      "barns-909-neibaur-vicki-2024-43",
      "barns-909-arneson-jim-2024-44",
      "barns-909-short-ken-2024-45",
      "barns-909-delvin-jerome-2024-46",
      "barns-909-shimek-jaime-2024-47",
      "barns-909-mick-westin-2024-48",
      "barns-909-renz-liz-2024-49",
      "barns-909-nelson-katie-2024-50",
      "barns-909-umc-inc-2024-51",
      "barns-909-bouchey-kevin-2024-52",
      "barns-909-small-contributions-2024-53",
      "barns-909-garcia-raul-2024-54",
      "barns-909-peurrung-anthony-2024-55",
      "barns-909-novakovich-shannon-2024-56",
      "barns-909-novakovich-michael-2024-57",
      "barns-909-blasdel-melissa-2024-58",
      "barns-909-morris-jeff-2024-59",
      "barns-909-washington-technology-industry-association-wtia-2024-60",
      "barns-909-small-contributions-2024-61",
      "barns-909-cypress-creek-renewables-development-llc-2024-62",
      "barns-909-law-office-of-patrick-d-mc-burney-2024-63",
      "barns-909-hedengren-david-2024-64",
      "barns-909-hedengren-marian-2024-65",
      "barns-909-lampson-william-2024-66",
      "barns-909-lampson-kate-2024-67",
      "barns-909-smitt-gary-2024-68",
      "barns-909-smitt-donna-2024-69",
      "barns-909-grabner-reagan-2024-70",
      "barns-909-grabner-lindsey-2024-71",
      "barns-909-ace-brian-2024-72",
      "barns-909-henry-staci-2024-73",
      "barns-909-raymond-james-2024-74",
      "barns-909-barber-shannon-2024-75",
      "barns-909-huber-monty-2024-76",
      "barns-909-fielding-cody-2024-77",
      "barns-909-fielding-candace-2024-78",
      "barns-909-arneson-jim-2024-79",
      "barns-909-hollingsworth-chris-2024-80",
      "barns-909-mullen-randy-2024-81",
      "barns-909-carlen-diana-2024-82",
      "barns-909-hale-kari-2024-83",
      "barns-909-ruiz-javier-2024-84",
      "barns-909-hatch-la-wanda-2024-85",
      "barns-909-moody-dean-2024-86",
      "barns-909-spanner-bruce-2024-87",
      "barns-909-spanner-mary-2024-88",
      "barns-909-brunson-kim-2024-89",
      "barns-909-sparkling-sensation-inc-2024-90",
      "barns-909-christensen-2024-91",
      "barns-909-parr-robert-2024-92",
      "barns-909-reeploeg-david-2024-93",
      "barns-909-heaston-suzanne-2024-94",
      "barns-909-heaston-suzanne-2024-95",
      "barns-909-heaston-dale-2024-96",
      "barns-909-heaston-dale-2024-97",
      "barns-909-haller-david-2024-98",
      "barns-909-haller-robin-2024-99",
      "barns-909-sandlin-bryan-2024-100",
      "barns-909-sandlin-deborah-2024-101",
      "barns-909-reyes-charles-2024-102",
      "barns-909-massey-consulting-llc-2024-103",
      "barns-909-simmons-steven-2024-104",
      "barns-909-simmons-shirley-2024-105",
      "barns-909-reeploeg-gretchen-2024-106",
      "barns-909-small-contributions-2024-107",
      "barns-909-clarke-bill-2024-108",
      "barns-909-house-republican-organizational-committee-2024-109",
      "barns-909-parr-robert-2024-110",
      "barns-909-delta-dental-2024-111",
      "barns-909-reynolds-american-inc-rai-services-company-2024-112",
      "barns-909-bilskis-richard-2024-113",
      "barns-909-west-staci-2024-114",
      "barns-909-henderson-destry-2024-115",
      "barns-909-small-contributions-2024-116",
      "barns-909-richey-jodi-2024-117",
      "barns-909-richey-bob-2024-118",
      "barns-909-wilson-claudia-2024-119",
      "barns-909-ownbey-nikki-2024-120",
      "barns-909-jacobs-ryan-2024-121",
      "barns-909-jacobs-morgen-2024-122",
      "barns-909-casey-paul-2024-123",
      "barns-909-hastings-colin-2024-124",
      "barns-909-howard-diahann-2024-125",
      "barns-909-bassett-melanie-2024-126",
      "barns-909-shimek-jaime-2024-127",
      "barns-909-morris-john-2024-128",
      "barns-909-heaston-suzanne-2024-129",
      "barns-909-heaston-dale-2024-130",
      "barns-909-massey-consulting-llc-2024-131",
      "barns-909-tri-city-eyes-2024-132",
      "barns-909-t-mobile-usa-inc-2024-133",
      "barns-909-mattson-lori-2024-134",
      "barns-909-gerber-michele-2024-135",
      "barns-909-gerber-eric-2024-136",
      "barns-909-francik-rebecca-2024-137",
      "barns-909-francik-joseph-2024-138",
      "barns-909-dietrich-darrick-2024-139",
      "barns-909-salon-remedi-2024-140",
      "barns-909-brewer-glenda-2024-141",
      "barns-909-mc-curley-dealerships-2024-142",
      "barns-909-hill-andrew-2024-143",
      "barns-909-bilskis-richard-2024-144",
      "barns-909-arbaugh-david-2024-145",
      "barns-909-washington-forest-protection-association-2024-146",
      "barns-909-sabey-corporation-2024-147",
      "barns-909-at-t-services-inc-2024-148",
      "barns-909-wa-state-tree-fruit-association-pac-2024-149",
      "barns-909-potato-pac-2024-150",
      "barns-909-cattle-pac-2024-151",
      "barns-909-amazon-com-services-llc-2024-152",
      "barns-909-altria-client-services-llc-2024-153",
      "barns-909-washington-state-auto-dealers-pac-2024-154",
      "barns-909-packaging-corporation-of-america-2024-155",
      "barns-909-associated-builders-and-contractors-of-wester-washington-pac-2024-156",
      "barns-909-amr-holdco-inc-2024-157",
      "barns-909-davita-2024-158",
      "barns-909-puget-sound-chapter-neca-pac-2024-159",
      "barns-909-lumen-technologies-service-group-2024-160",
      "barns-909-stubbs-ashley-2024-161",
      "barns-909-parr-robert-2024-162",
      "barns-909-davenport-jennifer-2024-163",
      "barns-909-reeploeg-david-2024-164",
      "barns-909-heaston-suzanne-2024-165",
      "barns-909-heaston-dale-2024-166",
      "barns-909-b-4-development-and-consulting-llc-2024-167",
      "barns-909-reeploeg-gretchen-2024-168",
      "barns-909-lampson-william-2024-169",
      "barns-909-davenport-thomas-2024-170",
      "barns-909-thompson-trent-2024-171",
      "barns-909-thompson-elizabeth-2024-172",
      "barns-909-helms-karen-2024-173",
      "barns-909-helms-jason-2024-174",
      "barns-909-davidson-duane-2024-175",
      "barns-909-center-vision-contact-lens-clinic-2024-176",
      "barns-909-small-contributions-2024-177",
      "barns-909-washington-affordable-housing-council-2024-178",
      "barns-909-washington-society-of-cpas-pac-2024-179",
      "barns-909-davita-2024-180",
      "barns-909-macpac-2024-181",
      "barns-909-washington-electric-cooperative-pac-2024-182",
      "barns-909-eschenberg-john-2024-183",
      "barns-909-osborne-andrew-2024-184",
      "barns-909-puget-sound-pilots-pac-2024-185",
      "barns-909-build-east-pac-2024-186",
      "barns-909-door-dash-inc-2024-187",
      "barns-909-washington-aggregates-concrete-association-2024-188",
      "barns-909-cullen-greg-2024-189",
      "barns-909-elenbaas-dan-2024-190",
      "barns-909-elenbaas-dan-2024-191",
      "barns-909-small-contributions-2024-192",
      "barns-909-cullen-greg-2024-193",
      "barns-909-buena-vista-property-management-2024-194",
      "barns-909-puget-sound-chapter-neca-pac-2024-460",
      "barns-909-altria-client-services-llc-2024-461",
      "barns-909-walmart-inc-2024-462",
      "barns-909-cal-portland-company-2024-463",
      "barns-909-hedengren-david-2024-464",
      "barns-909-hedengren-marian-2024-465",
      "barns-909-washington-wheat-pac-2024-466",
      "barns-909-avista-corp-2024-467",
      "barns-909-sabey-corporation-2024-468",
      "barns-909-sabey-corporation-2024-469",
      "barns-909-the-boeing-company-pac-2024-470",
      "barns-909-iron-workers-district-council-of-the-pacific-northwest-pac-2024-471",
      "barns-909-muckleshoot-indian-tribe-2024-472",
      "barns-909-spokane-teachers-credit-union-2024-473",
      "barns-909-washington-beverage-association-pac-2024-474",
      "barns-909-washington-state-assoc-of-fire-chiefs-pac-2024-475",
      "barns-909-bybee-brett-2024-484",
      "barns-909-feil-alma-2024-501",
      "barns-909-potato-pac-2024-502",
      "barns-909-credit-union-legislative-action-fund-2024-503",
      "barns-909-pemco-mutual-insurance-company-2024-504",
      "barns-909-amr-holdco-inc-2024-505",
      "barns-909-moveit-inc-2024-506",
      "barns-909-washington-oil-marketers-assoc-pac-2024-507",
      "barns-909-door-dash-inc-2024-508",
      "barns-909-washington-aggregates-concrete-association-2024-509",
      "barns-909-cascade-natural-gas-corporation-2024-510",
      "barns-909-life-science-washington-pac-2024-511",
      "barns-909-fisher-darrel-2024-513",
      "barns-909-fisher-a-jeanne-2024-514",
      "barns-909-amazon-com-services-llc-2024-552",
      "barns-909-packaging-corporation-of-america-2024-553",
      "barns-909-broadband-communications-association-of-washington-pac-2024-554",
      "barns-909-american-chemistry-council-2024-555",
      "barns-909-northwest-grocery-association-wa-pac-2024-556"
    ]
  },
  {
    "id": "barab-301-funding",
    "candidate": "BARAB  301",
    "unique_donors": 17,
    "total_raised": 6143,
    "total_cash": null,
    "total_in_kind": null,
    "donors": [
      "barab-301-puigh-barbara",
      "barab-301-blanche-barajas",
      "barab-301-small-contributions",
      "barab-301-wiswall-tara",
      "barab-301-fifer-frost-s",
      "barab-301-cole-schwartz-steven",
      "barab-301-mc-veety-sam",
      "barab-301-bass-janet",
      "barab-301-markyn-holly",
      "barab-301-marklyn-bill",
      "barab-301-simmons-kyle",
      "barab-301-nicholson-erik",
      "barab-301-dobkins-susan",
      "barab-301-anonymous-contributions"
    ],
    "donations": [
      "barab-301-puigh-barbara-2024-195",
      "barab-301-blanche-barajas-2024-196",
      "barab-301-small-contributions-2024-197",
      "barab-301-blanche-barajas-2024-198",
      "barab-301-wiswall-tara-2024-199",
      "barab-301-fifer-frost-s-2024-200",
      "barab-301-cole-schwartz-steven-2024-201",
      "barab-301-mc-veety-sam-2024-202",
      "barab-301-bass-janet-2024-203",
      "barab-301-small-contributions-2024-204",
      "barab-301-markyn-holly-2024-205",
      "barab-301-marklyn-bill-2024-206",
      "barab-301-simmons-kyle-2024-531",
      "barab-301-nicholson-erik-2024-532",
      "barab-301-dobkins-susan-2024-533",
      "barab-301-anonymous-contributions-2024-534",
      "barab-301-small-contributions-2024-535"
    ]
  },
  {
    "id": "mullr-301-funding",
    "candidate": "MULLR  301",
    "unique_donors": 3,
    "total_raised": 500,
    "total_cash": 500,
    "total_in_kind": 0,
    "donors": [
      "mullr-301-benjamin-charlotte",
      "mullr-301-tschirky-meri",
      "mullr-301-tschirky-ted"
    ],
    "donations": [
      "mullr-301-benjamin-charlotte-2024-207",
      "mullr-301-tschirky-meri-2024-521",
      "mullr-301-tschirky-ted-2024-522"
    ]
  },
  {
    "id": "browb-336-funding",
    "candidate": "BROWB--336",
    "unique_donors": 16,
    "total_raised": 7861,
    "total_cash": null,
    "total_in_kind": null,
    "donors": [
      "browb-336-whitmire-megan",
      "browb-336-bronson-joe-brown-bronson-j-brown",
      "browb-336-floyd-ben",
      "browb-336-floyd-lara",
      "browb-336-stam-jacqueline",
      "browb-336-kelly-kevin",
      "browb-336-kelly-elizabeth",
      "browb-336-call-kenneth",
      "browb-336-brown-michael",
      "browb-336-mickelsen-dalton-llc",
      "browb-336-tindell-alan-j",
      "browb-336-mc-bride-robert",
      "browb-336-quantum-legal-pllc",
      "browb-336-prescott-peggy",
      "browb-336-mustang-signs",
      "browb-336-chvatal-king-law-office"
    ],
    "donations": [
      "browb-336-whitmire-megan-2024-208",
      "browb-336-bronson-joe-brown-bronson-j-brown-2024-494",
      "browb-336-floyd-ben-2024-495",
      "browb-336-floyd-lara-2024-496",
      "browb-336-stam-jacqueline-2024-497",
      "browb-336-kelly-kevin-2024-498",
      "browb-336-kelly-elizabeth-2024-499",
      "browb-336-call-kenneth-2024-500",
      "browb-336-brown-michael-2024-537",
      "browb-336-mickelsen-dalton-llc-2024-538",
      "browb-336-tindell-alan-j-2024-539",
      "browb-336-mc-bride-robert-2024-540",
      "browb-336-quantum-legal-pllc-2024-541",
      "browb-336-prescott-peggy-2024-542",
      "browb-336-mustang-signs-2024-543",
      "browb-336-chvatal-king-law-office-2024-544"
    ]
  },
  {
    "id": "smarj-352-funding",
    "candidate": "SMARJ--352",
    "unique_donors": 1,
    "total_raised": 1172,
    "donors": [
      "smarj-352-jeff-j-smart"
    ],
    "donations": [
      "smarj-352-jeff-j-smart-2024-209"
    ]
  },
  {
    "id": "delvj-352-funding",
    "candidate": "DELVJ  352",
    "unique_donors": 14,
    "total_raised": 10350,
    "total_cash": 10350,
    "total_in_kind": 0,
    "donors": [
      "delvj-352-n-lampson-william",
      "delvj-352-markel-greg",
      "delvj-352-markel-carla",
      "delvj-352-mccurley-integrity-dealerships",
      "delvj-352-gerber-michelle",
      "delvj-352-gerber-eric",
      "delvj-352-slow-burn-real-estate-llc",
      "delvj-352-richland-firefighters-local-152",
      "delvj-352-plumbers-steamfitters-local-union-598",
      "delvj-352-brecke-allen-d-esq",
      "delvj-352-kennewick-union-fire-fighters-l-1296",
      "delvj-352-tri-cities-housing-council"
    ],
    "donations": [
      "delvj-352-n-lampson-william-2024-210",
      "delvj-352-markel-greg-2024-211",
      "delvj-352-markel-carla-2024-212",
      "delvj-352-mccurley-integrity-dealerships-2024-213",
      "delvj-352-gerber-michelle-2024-214",
      "delvj-352-gerber-eric-2024-215",
      "delvj-352-slow-burn-real-estate-llc-2024-480",
      "delvj-352-slow-burn-real-estate-llc-2024-481",
      "delvj-352-richland-firefighters-local-152-2024-492",
      "delvj-352-plumbers-steamfitters-local-union-598-2024-515",
      "delvj-352-brecke-allen-d-esq-2024-516",
      "delvj-352-n-lampson-william-2024-529",
      "delvj-352-kennewick-union-fire-fighters-l-1296-2024-530",
      "delvj-352-tri-cities-housing-council-2024-536"
    ]
  },
  {
    "id": "sants-301-funding",
    "candidate": "SANTS  301",
    "unique_donors": 11,
    "total_raised": 7140,
    "total_cash": 7140,
    "total_in_kind": 0,
    "donors": [
      "sants-301-thompson-roland",
      "sants-301-halle-charlene",
      "sants-301-small-contributions",
      "sants-301-sosa-buddy",
      "sants-301-sant-noman",
      "sants-301-sant-susan",
      "sants-301-markel-greg",
      "sants-301-markel-carla",
      "sants-301-hester-g-a",
      "sants-301-hester-michelle-l"
    ],
    "donations": [
      "sants-301-thompson-roland-2024-216",
      "sants-301-halle-charlene-2024-217",
      "sants-301-small-contributions-2024-218",
      "sants-301-sosa-buddy-2024-219",
      "sants-301-sant-noman-2024-545",
      "sants-301-sant-susan-2024-546",
      "sants-301-markel-greg-2024-547",
      "sants-301-markel-carla-2024-548",
      "sants-301-small-contributions-2024-549",
      "sants-301-hester-g-a-2024-550",
      "sants-301-hester-michelle-l-2024-551"
    ]
  },
  {
    "id": "baums-301-funding",
    "candidate": "BAUMS--301",
    "unique_donors": 2,
    "total_raised": 1043,
    "total_cash": null,
    "total_in_kind": null,
    "donors": [
      "baums-301-benjamin-charlotte",
      "baums-301-stephen-bauman"
    ],
    "donations": [
      "baums-301-benjamin-charlotte-2024-220",
      "baums-301-stephen-bauman-2024-221"
    ]
  },
  {
    "id": "conna-861-funding",
    "candidate": "CONNA--861",
    "unique_donors": 240,
    "total_raised": 128972,
    "total_cash": null,
    "total_in_kind": null,
    "donors": [
      "conna-861-puget-sound-chapter-neca-pac",
      "conna-861-wells-fargo-co-employee-pac",
      "conna-861-altria-client-services-llc",
      "conna-861-cal-portland-company",
      "conna-861-murray-brianna",
      "conna-861-washington-electric-cooperative-pac",
      "conna-861-entertainment-software-association",
      "conna-861-mc-mullan-david",
      "conna-861-washington-society-of-cp-as-pac",
      "conna-861-iron-workers-district-council-of-the-pnw",
      "conna-861-building-owners-and-managers-association-pac-of-washington-boma-pac",
      "conna-861-the-boeing-company-pac",
      "conna-861-muckleshoot-indian-tribe",
      "conna-861-southport-financial-services",
      "conna-861-amr-holdco-inc-american-medical-response",
      "conna-861-b-4-development-and-consulting-llc",
      "conna-861-wa-state-tree-fruit-association-pac",
      "conna-861-potato-pac",
      "conna-861-cattle-pac",
      "conna-861-sabey-corporation",
      "conna-861-washington-refuse-and-recycling-association-pac",
      "conna-861-puget-sound-energy",
      "conna-861-delta-dental",
      "conna-861-iupat-political-action-together-legislative-education-committee",
      "conna-861-connors-patrick",
      "conna-861-connors-jeanne",
      "conna-861-cooper-john",
      "conna-861-amazon-com-services-llc",
      "conna-861-packaging-corporation-of-america",
      "conna-861-associated-builders-and-contractors-of-western-washington-pac",
      "conna-861-dufault-jeremie",
      "conna-861-fick-james",
      "conna-861-bouchey-kevin",
      "conna-861-bouchey-renee",
      "conna-861-howard-diahann",
      "conna-861-heath-rick",
      "conna-861-hastings-colin",
      "conna-861-henderson-jodi",
      "conna-861-feil-alma",
      "conna-861-bouchey-joel",
      "conna-861-funk-sarah",
      "conna-861-ashby-steven",
      "conna-861-minutemen-press-of-kennewick",
      "conna-861-build-east-pac",
      "conna-861-usaa",
      "conna-861-naiop-washington-state-pac",
      "conna-861-state-farm-federal-pac",
      "conna-861-stevens-janet",
      "conna-861-stevens-rich",
      "conna-861-kroger",
      "conna-861-the-nichols-group-government-relations",
      "conna-861-associated-general-contractors-build-east-pac",
      "conna-861-porter-cheryl",
      "conna-861-washington-affordable-housing-council",
      "conna-861-washington-win-sponsored-by-maverick-gaming",
      "conna-861-washington-forest-protection-association",
      "conna-861-couture-travis",
      "conna-861-blankenship-jessica",
      "conna-861-shimek-jaime",
      "conna-861-mccurley-dealerships",
      "conna-861-blasdel-lonnie",
      "conna-861-blasdel-kathryn",
      "conna-861-bouchey-gary",
      "conna-861-bouchey-marianne",
      "conna-861-skipper-joshua",
      "conna-861-skipper-virginia",
      "conna-861-t-mobile",
      "conna-861-reffalt-noreen",
      "conna-861-thorpe-nancy",
      "conna-861-roach-patrick",
      "conna-861-roach-leeann",
      "conna-861-douglas-pete",
      "conna-861-novakovich-shannon",
      "conna-861-peurrung-anthony",
      "conna-861-novakovich-michael",
      "conna-861-walmart-inc",
      "conna-861-washbankpac-state",
      "conna-861-da-vita",
      "conna-861-hoover-mike",
      "conna-861-associated-builders-and-contractors-inland-pacific-chapter-inc-pac",
      "conna-861-small-contributions",
      "conna-861-wa-beverage-association-pac",
      "conna-861-washington-multi-family-housing-assoc-pac-account",
      "conna-861-sardinas-paula",
      "conna-861-rosano-vince",
      "conna-861-ace-brian",
      "conna-861-hollingsworth-chris",
      "conna-861-enterprise-holdings-inc-pac",
      "conna-861-washington-association-of-realtors-political-affairs-council",
      "conna-861-berglund-nikki",
      "conna-861-berglund-troy",
      "conna-861-smith-steffanie",
      "conna-861-hastings-doc",
      "conna-861-hastings-claire",
      "conna-861-lampson-kathy",
      "conna-861-lampson-william",
      "conna-861-keck-roy",
      "conna-861-den-hoed-helen",
      "conna-861-lampson-kathleen",
      "conna-861-carpenter-stephanie",
      "conna-861-novakovich-skip",
      "conna-861-short-ken",
      "conna-861-clarke-bill",
      "conna-861-torelli-charles",
      "conna-861-washington-optometric-pac",
      "conna-861-bnsf-railway-company",
      "conna-861-zurich-american-insurance-company",
      "conna-861-washington-state-podiatric-medical-association-podpac",
      "conna-861-wallace-robert",
      "conna-861-wallace-joan",
      "conna-861-nationwide-mutual-insurance-company",
      "conna-861-manufactured-housing-communities-of-washington-inc-pac",
      "conna-861-washington-collectors-association-pac-wacpac",
      "conna-861-wroa-pac",
      "conna-861-government-building-owners-lessors-association",
      "conna-861-washington-state-dental-pac",
      "conna-861-west-staci",
      "conna-861-washington-state-auto-dealers-pac",
      "conna-861-mpc-investment-fund-inc-marathon-petroleum-corporation",
      "conna-861-washington-hospitality-association-pac",
      "conna-861-washington-food-industry-association-pac",
      "conna-861-mc-bride-public-affairs-llc",
      "conna-861-microsoft",
      "conna-861-washington-oil-marketers-assoc-pac",
      "conna-861-northwest-natural-gas-co",
      "conna-861-ace-american-insurance-co-chubb",
      "conna-861-arbaugh-associates-inc",
      "conna-861-henderson-destry",
      "conna-861-pemco-mutual-insurance-company",
      "conna-861-wa-insurers-pac",
      "conna-861-service-corporation-international-political-action-committee",
      "conna-861-association-of-washington-business-pac",
      "conna-861-wa-charters-political-action-committee",
      "conna-861-haberling-j-tyler",
      "conna-861-haberling-noelia",
      "conna-861-washington-health-care-association-pac",
      "conna-861-underwood-kathy",
      "conna-861-morris-john",
      "conna-861-heaston-suzanne",
      "conna-861-heaston-dale",
      "conna-861-mc-curley-dealerships",
      "conna-861-massey-consulting-llc",
      "conna-861-mattson-lori",
      "conna-861-gerber-michele",
      "conna-861-gerber-eric",
      "conna-861-salon-remedi-chaune-fitzgerald",
      "conna-861-francik-rebecca",
      "conna-861-francik-jospeh",
      "conna-861-brewer-glenda",
      "conna-861-dietrich-darrick",
      "conna-861-center-vision-contact-lens-clinic",
      "conna-861-goodman-real-estate-inc",
      "conna-861-premera-blue-cross",
      "conna-861-becu",
      "conna-861-zillow-group-political-action-committee-zg-pac",
      "conna-861-hickerson-eunice",
      "conna-861-bailey-rodney",
      "conna-861-bailey-emily",
      "conna-861-macpac",
      "conna-861-fms-global-strategies",
      "conna-861-wa-beverage-association",
      "conna-861-parr-robert",
      "conna-861-alaska-airlines",
      "conna-861-chevron-policy-govt-public-affairs",
      "conna-861-gilead-sciences-inc",
      "conna-861-grieb-geri",
      "conna-861-brown-christopher",
      "conna-861-brown-linda",
      "conna-861-peters-louise",
      "conna-861-peters-jerry",
      "conna-861-davis-michael",
      "conna-861-davis-cathy",
      "conna-861-ringwood-gerry",
      "conna-861-house-republican-organizational-committee",
      "conna-861-cascade-pac",
      "conna-861-mc-cune-h",
      "conna-861-mccune-jonathon",
      "conna-861-hospitals-for-a-healthy-future-pac",
      "conna-861-washington-state-veterinary-medical-assn-inc-pac",
      "conna-861-point-digital-finance-inc",
      "conna-861-washington-state-assoc-of-fire-chiefs-pac",
      "conna-861-spokane-teachers-credit-union",
      "conna-861-unlock-technologies-inc",
      "conna-861-washington-wheat-pac",
      "conna-861-homecare-association-of-washington-hcaw-pac",
      "conna-861-low-sam",
      "conna-861-merck-sharp-dohme-llc",
      "conna-861-credit-union-legislative-action-fund",
      "conna-861-big-i-pac",
      "conna-861-washington-indian-gaming-association-campaign-for-tribal-self-reliance",
      "conna-861-puyallup-tribe-of-indians",
      "conna-861-doordash-inc",
      "conna-861-international-union-of-operating-engineers-local-302",
      "conna-861-cascade-natural-gas-company",
      "conna-861-american-property-casualty-insurance-association",
      "conna-861-alliance-for-automotive-innovation",
      "conna-861-northwest-grocery-association-pac"
    ],
    "donations": [
      "conna-861-puget-sound-chapter-neca-pac-2024-222",
      "conna-861-wells-fargo-co-employee-pac-2024-223",
      "conna-861-altria-client-services-llc-2024-224",
      "conna-861-cal-portland-company-2024-225",
      "conna-861-murray-brianna-2024-226",
      "conna-861-washington-electric-cooperative-pac-2024-227",
      "conna-861-entertainment-software-association-2024-228",
      "conna-861-mc-mullan-david-2024-229",
      "conna-861-washington-society-of-cp-as-pac-2024-230",
      "conna-861-iron-workers-district-council-of-the-pnw-2024-231",
      "conna-861-building-owners-and-managers-association-pac-of-washington-boma-pac-2024-232",
      "conna-861-the-boeing-company-pac-2024-233",
      "conna-861-muckleshoot-indian-tribe-2024-234",
      "conna-861-southport-financial-services-2024-235",
      "conna-861-amr-holdco-inc-american-medical-response-2024-236",
      "conna-861-b-4-development-and-consulting-llc-2024-237",
      "conna-861-wa-state-tree-fruit-association-pac-2024-238",
      "conna-861-potato-pac-2024-239",
      "conna-861-cattle-pac-2024-240",
      "conna-861-sabey-corporation-2024-241",
      "conna-861-washington-refuse-and-recycling-association-pac-2024-242",
      "conna-861-puget-sound-energy-2024-243",
      "conna-861-puget-sound-energy-2024-244",
      "conna-861-delta-dental-2024-245",
      "conna-861-iupat-political-action-together-legislative-education-committee-2024-246",
      "conna-861-connors-patrick-2024-247",
      "conna-861-connors-jeanne-2024-248",
      "conna-861-cooper-john-2024-249",
      "conna-861-amazon-com-services-llc-2024-250",
      "conna-861-packaging-corporation-of-america-2024-251",
      "conna-861-associated-builders-and-contractors-of-western-washington-pac-2024-252",
      "conna-861-dufault-jeremie-2024-253",
      "conna-861-fick-james-2024-254",
      "conna-861-bouchey-kevin-2024-255",
      "conna-861-bouchey-renee-2024-256",
      "conna-861-howard-diahann-2024-257",
      "conna-861-heath-rick-2024-258",
      "conna-861-hastings-colin-2024-259",
      "conna-861-henderson-jodi-2024-260",
      "conna-861-feil-alma-2024-261",
      "conna-861-bouchey-joel-2024-262",
      "conna-861-funk-sarah-2024-263",
      "conna-861-ashby-steven-2024-264",
      "conna-861-minutemen-press-of-kennewick-2024-265",
      "conna-861-build-east-pac-2024-266",
      "conna-861-usaa-2024-267",
      "conna-861-naiop-washington-state-pac-2024-268",
      "conna-861-state-farm-federal-pac-2024-269",
      "conna-861-stevens-janet-2024-270",
      "conna-861-stevens-rich-2024-271",
      "conna-861-kroger-2024-272",
      "conna-861-the-nichols-group-government-relations-2024-273",
      "conna-861-associated-general-contractors-build-east-pac-2024-274",
      "conna-861-porter-cheryl-2024-275",
      "conna-861-washington-affordable-housing-council-2024-276",
      "conna-861-washington-affordable-housing-council-2024-277",
      "conna-861-washington-win-sponsored-by-maverick-gaming-2024-278",
      "conna-861-washington-forest-protection-association-2024-279",
      "conna-861-couture-travis-2024-280",
      "conna-861-blankenship-jessica-2024-281",
      "conna-861-shimek-jaime-2024-282",
      "conna-861-mccurley-dealerships-2024-283",
      "conna-861-blasdel-lonnie-2024-284",
      "conna-861-blasdel-kathryn-2024-285",
      "conna-861-bouchey-gary-2024-286",
      "conna-861-bouchey-marianne-2024-287",
      "conna-861-skipper-joshua-2024-288",
      "conna-861-skipper-virginia-2024-289",
      "conna-861-t-mobile-2024-290",
      "conna-861-reffalt-noreen-2024-291",
      "conna-861-thorpe-nancy-2024-292",
      "conna-861-roach-patrick-2024-293",
      "conna-861-roach-leeann-2024-294",
      "conna-861-douglas-pete-2024-295",
      "conna-861-novakovich-shannon-2024-296",
      "conna-861-peurrung-anthony-2024-297",
      "conna-861-novakovich-michael-2024-298",
      "conna-861-walmart-inc-2024-299",
      "conna-861-state-farm-federal-pac-2024-300",
      "conna-861-washbankpac-state-2024-301",
      "conna-861-washbankpac-state-2024-302",
      "conna-861-da-vita-2024-303",
      "conna-861-hoover-mike-2024-304",
      "conna-861-associated-builders-and-contractors-inland-pacific-chapter-inc-pac-2024-305",
      "conna-861-small-contributions-2024-306",
      "conna-861-wa-beverage-association-pac-2024-307",
      "conna-861-small-contributions-2024-308",
      "conna-861-washington-multi-family-housing-assoc-pac-account-2024-309",
      "conna-861-washington-multi-family-housing-assoc-pac-account-2024-310",
      "conna-861-sardinas-paula-2024-311",
      "conna-861-small-contributions-2024-312",
      "conna-861-rosano-vince-2024-313",
      "conna-861-ace-brian-2024-314",
      "conna-861-hollingsworth-chris-2024-315",
      "conna-861-enterprise-holdings-inc-pac-2024-316",
      "conna-861-washington-association-of-realtors-political-affairs-council-2024-317",
      "conna-861-washington-association-of-realtors-political-affairs-council-2024-318",
      "conna-861-berglund-nikki-2024-319",
      "conna-861-berglund-troy-2024-320",
      "conna-861-smith-steffanie-2024-321",
      "conna-861-hastings-doc-2024-322",
      "conna-861-hastings-claire-2024-323",
      "conna-861-lampson-kathy-2024-324",
      "conna-861-lampson-william-2024-325",
      "conna-861-keck-roy-2024-326",
      "conna-861-den-hoed-helen-2024-327",
      "conna-861-lampson-kathleen-2024-328",
      "conna-861-carpenter-stephanie-2024-329",
      "conna-861-novakovich-skip-2024-330",
      "conna-861-novakovich-shannon-2024-331",
      "conna-861-short-ken-2024-332",
      "conna-861-clarke-bill-2024-333",
      "conna-861-torelli-charles-2024-334",
      "conna-861-washington-refuse-and-recycling-association-pac-2024-335",
      "conna-861-washington-optometric-pac-2024-336",
      "conna-861-bnsf-railway-company-2024-337",
      "conna-861-bnsf-railway-company-2024-338",
      "conna-861-zurich-american-insurance-company-2024-339",
      "conna-861-washington-state-podiatric-medical-association-podpac-2024-340",
      "conna-861-wallace-robert-2024-341",
      "conna-861-wallace-joan-2024-342",
      "conna-861-nationwide-mutual-insurance-company-2024-343",
      "conna-861-manufactured-housing-communities-of-washington-inc-pac-2024-344",
      "conna-861-manufactured-housing-communities-of-washington-inc-pac-2024-345",
      "conna-861-washington-collectors-association-pac-wacpac-2024-346",
      "conna-861-wroa-pac-2024-347",
      "conna-861-government-building-owners-lessors-association-2024-348",
      "conna-861-washington-state-dental-pac-2024-349",
      "conna-861-washington-state-dental-pac-2024-350",
      "conna-861-west-staci-2024-351",
      "conna-861-washington-state-auto-dealers-pac-2024-352",
      "conna-861-mpc-investment-fund-inc-marathon-petroleum-corporation-2024-353",
      "conna-861-washington-hospitality-association-pac-2024-354",
      "conna-861-washington-food-industry-association-pac-2024-355",
      "conna-861-mc-bride-public-affairs-llc-2024-356",
      "conna-861-microsoft-2024-357",
      "conna-861-washington-oil-marketers-assoc-pac-2024-358",
      "conna-861-northwest-natural-gas-co-2024-359",
      "conna-861-walmart-inc-2024-360",
      "conna-861-ace-american-insurance-co-chubb-2024-361",
      "conna-861-arbaugh-associates-inc-2024-362",
      "conna-861-henderson-destry-2024-363",
      "conna-861-pemco-mutual-insurance-company-2024-364",
      "conna-861-wa-insurers-pac-2024-365",
      "conna-861-service-corporation-international-political-action-committee-2024-366",
      "conna-861-washington-food-industry-association-pac-2024-367",
      "conna-861-association-of-washington-business-pac-2024-368",
      "conna-861-amr-holdco-inc-american-medical-response-2024-369",
      "conna-861-amr-holdco-inc-american-medical-response-2024-370",
      "conna-861-wa-charters-political-action-committee-2024-371",
      "conna-861-wa-charters-political-action-committee-2024-372",
      "conna-861-haberling-j-tyler-2024-373",
      "conna-861-haberling-noelia-2024-374",
      "conna-861-washington-hospitality-association-pac-2024-375",
      "conna-861-puget-sound-chapter-neca-pac-2024-376",
      "conna-861-altria-client-services-llc-2024-377",
      "conna-861-pemco-mutual-insurance-company-2024-378",
      "conna-861-washington-health-care-association-pac-2024-379",
      "conna-861-underwood-kathy-2024-380",
      "conna-861-morris-john-2024-381",
      "conna-861-heaston-suzanne-2024-382",
      "conna-861-heaston-dale-2024-383",
      "conna-861-mc-curley-dealerships-2024-384",
      "conna-861-massey-consulting-llc-2024-385",
      "conna-861-mattson-lori-2024-386",
      "conna-861-gerber-michele-2024-387",
      "conna-861-gerber-eric-2024-388",
      "conna-861-salon-remedi-chaune-fitzgerald-2024-389",
      "conna-861-francik-rebecca-2024-390",
      "conna-861-francik-jospeh-2024-391",
      "conna-861-brewer-glenda-2024-392",
      "conna-861-dietrich-darrick-2024-393",
      "conna-861-center-vision-contact-lens-clinic-2024-394",
      "conna-861-southport-financial-services-2024-395",
      "conna-861-southport-financial-services-2024-396",
      "conna-861-the-nichols-group-government-relations-2024-397",
      "conna-861-goodman-real-estate-inc-2024-398",
      "conna-861-goodman-real-estate-inc-2024-399",
      "conna-861-usaa-2024-400",
      "conna-861-premera-blue-cross-2024-401",
      "conna-861-wa-insurers-pac-2024-402",
      "conna-861-becu-2024-403",
      "conna-861-zillow-group-political-action-committee-zg-pac-2024-404",
      "conna-861-hickerson-eunice-2024-405",
      "conna-861-bailey-rodney-2024-406",
      "conna-861-bailey-emily-2024-407",
      "conna-861-small-contributions-2024-408",
      "conna-861-macpac-2024-409",
      "conna-861-fms-global-strategies-2024-410",
      "conna-861-wa-beverage-association-2024-411",
      "conna-861-parr-robert-2024-412",
      "conna-861-alaska-airlines-2024-413",
      "conna-861-chevron-policy-govt-public-affairs-2024-414",
      "conna-861-gilead-sciences-inc-2024-415",
      "conna-861-grieb-geri-2024-416",
      "conna-861-brown-christopher-2024-417",
      "conna-861-brown-linda-2024-418",
      "conna-861-peters-louise-2024-419",
      "conna-861-peters-jerry-2024-420",
      "conna-861-davis-michael-2024-421",
      "conna-861-davis-cathy-2024-422",
      "conna-861-ringwood-gerry-2024-423",
      "conna-861-house-republican-organizational-committee-2024-424",
      "conna-861-cascade-pac-2024-425",
      "conna-861-cascade-pac-2024-426",
      "conna-861-mc-cune-h-2024-427",
      "conna-861-mccune-jonathon-2024-428",
      "conna-861-sabey-corporation-2024-451",
      "conna-861-sabey-corporation-2024-452",
      "conna-861-hospitals-for-a-healthy-future-pac-2024-453",
      "conna-861-washington-state-veterinary-medical-assn-inc-pac-2024-454",
      "conna-861-point-digital-finance-inc-2024-455",
      "conna-861-hollingsworth-chris-2024-456",
      "conna-861-washington-state-assoc-of-fire-chiefs-pac-2024-457",
      "conna-861-spokane-teachers-credit-union-2024-458",
      "conna-861-unlock-technologies-inc-2024-459",
      "conna-861-washington-wheat-pac-2024-476",
      "conna-861-homecare-association-of-washington-hcaw-pac-2024-477",
      "conna-861-low-sam-2024-478",
      "conna-861-merck-sharp-dohme-llc-2024-479",
      "conna-861-credit-union-legislative-action-fund-2024-482",
      "conna-861-big-i-pac-2024-483",
      "conna-861-potato-pac-2024-485",
      "conna-861-washington-oil-marketers-assoc-pac-2024-486",
      "conna-861-washington-indian-gaming-association-campaign-for-tribal-self-reliance-2024-487",
      "conna-861-puyallup-tribe-of-indians-2024-488",
      "conna-861-doordash-inc-2024-489",
      "conna-861-washington-win-sponsored-by-maverick-gaming-2024-490",
      "conna-861-washington-win-sponsored-by-maverick-gaming-2024-491",
      "conna-861-international-union-of-operating-engineers-local-302-2024-493",
      "conna-861-cascade-natural-gas-company-2024-512",
      "conna-861-gilead-sciences-inc-2024-517",
      "conna-861-iupat-political-action-together-legislative-education-committee-2024-518",
      "conna-861-american-property-casualty-insurance-association-2024-519",
      "conna-861-packaging-corporation-of-america-2024-523",
      "conna-861-alliance-for-automotive-innovation-2024-524",
      "conna-861-northwest-grocery-association-pac-2024-525",
      "conna-861-hollingsworth-chris-2024-526",
      "conna-861-amazon-com-services-llc-2024-527",
      "conna-861-washington-health-care-association-pac-2024-528"
    ]
  },
  {
    "id": "chrij-336-funding",
    "candidate": "CHRIJ--336",
    "unique_donors": 5,
    "total_raised": 976,
    "total_cash": null,
    "total_in_kind": null,
    "donors": [
      "chrij-336-sahota-pritam-s",
      "chrij-336-small-contributions",
      "chrij-336-john-christenson",
      "chrij-336-john-eric-christenson-john-christenson"
    ],
    "donations": [
      "chrij-336-sahota-pritam-s-2024-429",
      "chrij-336-small-contributions-2024-442",
      "chrij-336-john-christenson-2024-443",
      "chrij-336-john-eric-christenson-john-christenson-2024-450",
      "chrij-336-sahota-pritam-s-2024-520"
    ]
  },
  {
    "id": "kenna-110-funding",
    "candidate": "KENNA--110",
    "unique_donors": 18,
    "total_raised": 7630,
    "total_cash": null,
    "total_in_kind": null,
    "donors": [
      "kenna-110-kennedy-john",
      "kenna-110-ana-ruiz-kennedy",
      "kenna-110-rodriguez-salvador",
      "kenna-110-tracy-chris",
      "kenna-110-roach-nancy",
      "kenna-110-franklin-county-democratic-central-committee",
      "kenna-110-griffith-brian",
      "kenna-110-armijo-ana",
      "kenna-110-martin-joni",
      "kenna-110-small-contributions",
      "kenna-110-lindsey-lori",
      "kenna-110-cadwell-jillian",
      "kenna-110-roach-john",
      "kenna-110-pennell-bill",
      "kenna-110-fitzgerald-chaune"
    ],
    "donations": [
      "kenna-110-kennedy-john-2024-430",
      "kenna-110-kennedy-john-2024-431",
      "kenna-110-kennedy-john-2024-432",
      "kenna-110-ana-ruiz-kennedy-2024-433",
      "kenna-110-rodriguez-salvador-2024-434",
      "kenna-110-tracy-chris-2024-435",
      "kenna-110-roach-nancy-2024-436",
      "kenna-110-franklin-county-democratic-central-committee-2024-437",
      "kenna-110-griffith-brian-2024-438",
      "kenna-110-armijo-ana-2024-439",
      "kenna-110-martin-joni-2024-440",
      "kenna-110-small-contributions-2024-441",
      "kenna-110-lindsey-lori-2024-444",
      "kenna-110-cadwell-jillian-2024-445",
      "kenna-110-roach-john-2024-446",
      "kenna-110-pennell-bill-2024-447",
      "kenna-110-fitzgerald-chaune-2024-448",
      "kenna-110-small-contributions-2024-449"
    ]
  }
]